agentform_cli/__init__.py
agentform_cli/agentform_compiler/__init__.py
agentform_cli/agentform_compiler/agentform_ast.py
agentform_cli/agentform_compiler/agentform_grammar.lark
agentform_cli/agentform_compiler/agentform_module_loader.py
agentform_cli/agentform_compiler/agentform_module_resolver.py
agentform_cli/agentform_compiler/agentform_normalizer.py
agentform_cli/agentform_compiler/agentform_parser.py
agentform_cli/agentform_compiler/agentform_resolver.py
agentform_cli/agentform_compiler/agentform_validator.py
agentform_cli/agentform_compiler/compiler.py
agentform_cli/agentform_compiler/credentials.py
agentform_cli/agentform_compiler/ir_generator.py
agentform_cli/agentform_compiler/parser.py
agentform_cli/agentform_compiler/py.typed
agentform_cli/agentform_compiler/validator.py
agentform_cli/agentform_mcp/__init__.py
agentform_cli/agentform_mcp/client.py
agentform_cli/agentform_mcp/py.typed
agentform_cli/agentform_mcp/server.py
agentform_cli/agentform_mcp/types.py
agentform_cli/agentform_runtime/__init__.py
agentform_cli/agentform_runtime/approval.py
agentform_cli/agentform_runtime/engine.py
agentform_cli/agentform_runtime/llm.py
agentform_cli/agentform_runtime/logging_config.py
agentform_cli/agentform_runtime/policy.py
agentform_cli/agentform_runtime/py.typed
agentform_cli/agentform_runtime/state.py
agentform_cli/agentform_runtime/tracing.py
agentform_cli/agentform_schema/__init__.py
agentform_cli/agentform_schema/ir.py
agentform_cli/agentform_schema/models.py
agentform_cli/agentform_schema/py.typed
agentform_cli/agentform_schema/version.py
agentform_cli/commands/__init__.py
agentform_cli/commands/compile.py
agentform_cli/commands/init.py
agentform_cli/commands/run.py
agentform_cli/commands/validate.py
agentform_cli/main.py
agentform_cli/provider_packages.py
agentform_cli-0.0.811.dist-info/METADATA
agentform_cli-0.0.811.dist-info/WHEEL
agentform_cli-0.0.811.dist-info/entry_points.txt
agentform_cli-0.0.811.dist-info/RECORD
